{"solution":[{"end_time":113,"coalition":[0, 1, 2, 3, 4, 12]},{"end_time":75,"coalition":[1, 14]},{"end_time":83,"coalition":[2, 14]},{"end_time":5,"coalition":[4]},{"end_time":102,"coalition":[3, 14]},{"end_time":5,"coalition":[5]},{"end_time":156,"coalition":[0, 6, 14]},{"end_time":4,"coalition":[7]},null,null,null,null,{"end_time":20,"coalition":[12]},null,{"end_time":10,"coalition":[14]},{"end_time":5,"coalition":[15]},null,null,null,{"end_time":4,"coalition":[19]},null,{"end_time":4,"coalition":[19]},{"end_time":5,"coalition":[4]},null,null,null],"metrics":{"average_travel_time":1.0,"comp_time_nano":66064721637,"completed_task_percentage":0.53846157}}